zvdata
