Metadata-Version: 2.1
Name: zvdata
Version: 1.2.1
Summary: an extendable library for recording and analyzing data
Home-page: https://github.com/zvtvz/zvdata
Author: foolcage
Author-email: 5533061@qq.com
License: UNKNOWN
Project-URL: Bug Reports, https://github.com/zvtvz/zvdata/issues
Project-URL: Funding, https://www.foolcage.com
Project-URL: Say Thanks!, https://saythanks.io/to/foolcage
Project-URL: Source, https://github.com/zvtvz/zvdata
Keywords: spider pandas data-science data-cleaning sqlalchemy
Platform: UNKNOWN
Classifier: Development Status :: 5 - Production/Stable
Classifier: Intended Audience :: Developers
Classifier: Intended Audience :: Customer Service
Classifier: Intended Audience :: Education
Classifier: Intended Audience :: Financial and Insurance Industry
Classifier: Topic :: Software Development :: Build Tools
Classifier: Topic :: Office/Business :: Financial :: Investment
Classifier: License :: OSI Approved :: MIT License
Classifier: Programming Language :: Python :: 3.6
